plasclass/__init__.py
plasclass/plasclass.py
plasclass/plasclass_utils.py
plasclass/train.py
plasclass/data/m1000
plasclass/data/m10000
plasclass/data/m100000
plasclass/data/m500000
plasclass/data/s1000
plasclass/data/s10000
plasclass/data/s100000
plasclass/data/s500000
plasclass-0.1.data/scripts/classify_fasta.py
plasclass-0.1.data/scripts/train.py
plasclass-0.1.dist-info/LICENSE
plasclass-0.1.dist-info/METADATA
plasclass-0.1.dist-info/WHEEL
plasclass-0.1.dist-info/top_level.txt
plasclass-0.1.dist-info/RECORD
