Metadata-Version: 2.1
Name: plasclass
Version: 0.1
Summary: Classification of plasmid sequences
Home-page: https://github.com/Shamir-Lab/PlasClass
Author: David Pellow
Author-email: dpellow@mail.tau.ac.il
License: UNKNOWN
Platform: UNKNOWN
Classifier: Programming Language :: Python :: 3.7
Classifier: License :: OSI Approved :: MIT License
Classifier: Operating System :: OS Independent
Requires-Dist: scipy (==1.3.2)
Requires-Dist: scikit-learn (==0.21.3)
Requires-Dist: joblib (==0.14)
Requires-Dist: numpy (==1.17.4)
